aula_03/ELTD10-Projeto/src/atividade3.v
module atividade3 (
     input [31:0] val_in,     //Entrada de 32-bits
    output [31:0] val_out_32, //Saida de 32-bits
    output [15:0] val_out_16, //Saída de 16-bits
     output [7:0] val_out_8,  //Saída de 8-bits
     output [3:0] val_out_4   //Saída de 4-bits
);
    assign val_out_32 = val_in; //Atribui o valor de entrada diretamente à saída de 32-bits
    assign val_out_16 = val_in[15:0]; //Atribui os 16 bits menos significativos à saída de 16-bits
    assign val_out_8 = val_in[7:0]; //Atribui os 8 bits menos significativos à saída de 8-bits
    assign val_out_4 = val_in[3:0]; //Atribui os 4 bits menos significativos à saída de 4-bits
endmodule

aula_03/ELTD10-Projeto/src/atividade3_tb.v
module atividade3_tb;
    reg [31:0] val_in;
    wire [31:0] val_out_32;
    wire [15:0] val_out_16;
    wire [7:0] val_out_8;
    wire [3:0] val_out_4;
    // Configuração do dump para visualização
    initial begin
        $dumpfile("sim/atividade3_tb.vcd");
        $dumpvars(0, atividade3_tb);
    end
    // Instancia o módulo atividade3
    atividade3 uut (
        .val_in(val_in),
        .val_out_32(val_out_32),
        .val_out_16(val_out_16),
        .val_out_8(val_out_8),
        .val_out_4(val_out_4)
    );
    // Bloco inicial para aplicar os testes
    initial begin
        $monitor("Time=%0d | val_in=%d | val_out_32=%d | val_out_16=%d | val_out_8=%d | val_out_4=%d",
                 $time, val_in, val_out_32, val_out_16, val_out_8, val_out_4);
        
        for (val_in = 0; val_in < 50; val_in = val_in + 1) begin
            #10;
        end
        
        $finish;
    end
endmodule

aula_03/ELTD10-Projeto/sim/atividade3_tb.vcd
$date
	Fri Apr 10 09:37:16 2026
$end
$version
	Icarus Verilog
$end
$timescale
	1s
$end
$scope module atividade3_tb $end
$var wire 8 ! val_out_8 [7:0] $end
$var wire 4 " val_out_4 [3:0] $end
$var wire 32 # val_out_32 [31:0] $end
$var wire 16 $ val_out_16 [15:0] $end
$var reg 32 % val_in [31:0] $end
$scope module uut $end
$var wire 32 & val_in [31:0] $end
$var wire 32 ' val_out_32 [31:0] $end
$var wire 8 ( val_out_8 [7:0] $end
$var wire 4 ) val_out_4 [3:0] $end
$var wire 16 * val_out_16 [15:0] $end
$upscope $end
$upscope $end
$enddefinitions $end
$comment Show the parameter values. $end
$dumpall
$end
#0
$dumpvars
b0 *
b0 )
b0 (
b0 '
b0 &
b0 %
b0 $
b0 #
b0 "
b0 !
$end
#10
b1 $
b1 *
b1 !
b1 (
b1 "
b1 )
b1 #
b1 '
b1 %
b1 &
#20
b10 $
b10 *
b10 !
b10 (
b10 "
b10 )
b10 #
b10 '
b10 %
b10 &
#30
b11 $
b11 *
b11 !
b11 (
b11 "
b11 )
b11 #
b11 '
b11 %
b11 &
#40
b100 $
b100 *
b100 !
b100 (
b100 "
b100 )
b100 #
b100 '
b100 %
b100 &
#50
b101 $
b101 *
b101 !
b101 (
b101 "
b101 )
b101 #
b101 '
b101 %
b101 &
#60
b110 $
b110 *
b110 !
b110 (
b110 "
b110 )
b110 #
b110 '
b110 %
b110 &
#70
b111 $
b111 *
b111 !
b111 (
b111 "
b111 )
b111 #
b111 '
b111 %
b111 &
#80
b1000 $
b1000 *
b1000 !
b1000 (
b1000 "
b1000 )
b1000 #
b1000 '
b1000 %
b1000 &
#90
b1001 $
b1001 *
b1001 !
b1001 (
b1001 "
b1001 )
b1001 #
b1001 '
b1001 %
b1001 &
#100
b1010 $
b1010 *
b1010 !
b1010 (
b1010 "
b1010 )
b1010 #
b1010 '
b1010 %
b1010 &
#110
b1011 $
b1011 *
b1011 !
b1011 (
b1011 "
b1011 )
b1011 #
b1011 '
b1011 %
b1011 &
#120
b1100 $
b1100 *
b1100 !
b1100 (
b1100 "
b1100 )
b1100 #
b1100 '
b1100 %
b1100 &
#130
b1101 $
b1101 *
b1101 !
b1101 (
b1101 "
b1101 )
b1101 #
b1101 '
b1101 %
b1101 &
#140
b1110 $
b1110 *
b1110 !
b1110 (
b1110 "
b1110 )
b1110 #
b1110 '
b1110 %
b1110 &
#150
b1111 $
b1111 *
b1111 !
b1111 (
b1111 "
b1111 )
b1111 #
b1111 '
b1111 %
b1111 &
#160
b10000 $
b10000 *
b10000 !
b10000 (
b0 "
b0 )
b10000 #
b10000 '
b10000 %
b10000 &
#170
b10001 $
b10001 *
b10001 !
b10001 (
b1 "
b1 )
b10001 #
b10001 '
b10001 %
b10001 &
#180
b10010 $
b10010 *
b10010 !
b10010 (
b10 "
b10 )
b10010 #
b10010 '
b10010 %
b10010 &
#190
b10011 $
b10011 *
b10011 !
b10011 (
b11 "
b11 )
b10011 #
b10011 '
b10011 %
b10011 &
#200
b10100 $
b10100 *
b10100 !
b10100 (
b100 "
b100 )
b10100 #
b10100 '
b10100 %
b10100 &
#210
b10101 $
b10101 *
b10101 !
b10101 (
b101 "
b101 )
b10101 #
b10101 '
b10101 %
b10101 &
#220
b10110 $
b10110 *
b10110 !
b10110 (
b110 "
b110 )
b10110 #
b10110 '
b10110 %
b10110 &
#230
b10111 $
b10111 *
b10111 !
b10111 (
b111 "
b111 )
b10111 #
b10111 '
b10111 %
b10111 &
#240
b11000 $
b11000 *
b11000 !
b11000 (
b1000 "
b1000 )
b11000 #
b11000 '
b11000 %
b11000 &
#250
b11001 $
b11001 *
b11001 !
b11001 (
b1001 "
b1001 )
b11001 #
b11001 '
b11001 %
b11001 &
#260
b11010 $
b11010 *
b11010 !
b11010 (
b1010 "
b1010 )
b11010 #
b11010 '
b11010 %
b11010 &
#270
b11011 $
b11011 *
b11011 !
b11011 (
b1011 "
b1011 )
b11011 #
b11011 '
b11011 %
b11011 &
#280
b11100 $
b11100 *
b11100 !
b11100 (
b1100 "
b1100 )
b11100 #
b11100 '
b11100 %
b11100 &
#290
b11101 $
b11101 *
b11101 !
b11101 (
b1101 "
b1101 )
b11101 #
b11101 '
b11101 %
b11101 &
#300
b11110 $
b11110 *
b11110 !
b11110 (
b1110 "
b1110 )
b11110 #
b11110 '
b11110 %
b11110 &
#310
b11111 $
b11111 *
b11111 !
b11111 (
b1111 "
b1111 )
b11111 #
b11111 '
b11111 %
b11111 &
#320
b100000 $
b100000 *
b100000 !
b100000 (
b0 "
b0 )
b100000 #
b100000 '
b100000 %
b100000 &
#330
b100001 $
b100001 *
b100001 !
b100001 (
b1 "
b1 )
b100001 #
b100001 '
b100001 %
b100001 &
#340
b100010 $
b100010 *
b100010 !
b100010 (
b10 "
b10 )
b100010 #
b100010 '
b100010 %
b100010 &
#350
b100011 $
b100011 *
b100011 !
b100011 (
b11 "
b11 )
b100011 #
b100011 '
b100011 %
b100011 &
#360
b100100 $
b100100 *
b100100 !
b100100 (
b100 "
b100 )
b100100 #
b100100 '
b100100 %
b100100 &
#370
b100101 $
b100101 *
b100101 !
b100101 (
b101 "
b101 )
b100101 #
b100101 '
b100101 %
b100101 &
#380
b100110 $
b100110 *
b100110 !
b100110 (
b110 "
b110 )
b100110 #
b100110 '
b100110 %
b100110 &
#390
b100111 $
b100111 *
b100111 !
b100111 (
b111 "
b111 )
b100111 #
b100111 '
b100111 %
b100111 &
#400
b101000 $
b101000 *
b101000 !
b101000 (
b1000 "
b1000 )
b101000 #
b101000 '
b101000 %
b101000 &
#410
b101001 $
b101001 *
b101001 !
b101001 (
b1001 "
b1001 )
b101001 #
b101001 '
b101001 %
b101001 &
#420
b101010 $
b101010 *
b101010 !
b101010 (
b1010 "
b1010 )
b101010 #
b101010 '
b101010 %
b101010 &
#430
b101011 $
b101011 *
b101011 !
b101011 (
b1011 "
b1011 )
b101011 #
b101011 '
b101011 %
b101011 &
#440
b101100 $
b101100 *
b101100 !
b101100 (
b1100 "
b1100 )
b101100 #
b101100 '
b101100 %
b101100 &
#450
b101101 $
b101101 *
b101101 !
b101101 (
b1101 "
b1101 )
b101101 #
b101101 '
b101101 %
b101101 &
#460
b101110 $
b101110 *
b101110 !
b101110 (
b1110 "
b1110 )
b101110 #
b101110 '
b101110 %
b101110 &
#470
b101111 $
b101111 *
b101111 !
b101111 (
b1111 "
b1111 )
b101111 #
b101111 '
b101111 %
b101111 &
#480
b110000 $
b110000 *
b110000 !
b110000 (
b0 "
b0 )
b110000 #
b110000 '
b110000 %
b110000 &
#490
b110001 $
b110001 *
b110001 !
b110001 (
b1 "
b1 )
b110001 #
b110001 '
b110001 %
b110001 &
#500
b110010 $
b110010 *
b110010 !
b110010 (
b10 "
b10 )
b110010 #
b110010 '
b110010 %
b110010 &
