aula_05/src/atividade1.v
module atividade1 (
    input A,   //!Entrada A
    input B,   //!Entrada B
    input C,   //!Entrada C
    output fm, //!forma de soma de produtos, fm,
    output fM, //!forma de produtos de soma, fM e
    output fs  //!forma simplificada, fs 
);
    //Usar fluxo de dados (|, &, ~)
    //Forma de soma de produtos, fm 
    assign fm = (~A & ~B & ~C) | (~A & B & ~C) | (A & ~B & ~C) | (A & B & ~C);
    //Forma de produtos de soma, fM
    assign fM = (A | B | ~C) & (A | ~B | ~C) & (~A | B | ~C) & (~A | ~B | ~C);
    
    //Forma simplificada, fs
    assign fs = ~C;
    
endmodule

aula_05/src/atividade1_tb.v
module atividade1_tb;
    reg A, B, C; // Entradas
    wire fm, fM, fs; // Saídas

    //dumpfile
    initial begin
        $dumpfile("sim/atividade1_tb.vcd");
        $dumpvars(0, atividade1_tb);
    end
    
    // Instancia o módulo a ser testado
    atividade1 uut (
        .A(A),
        .B(B),
        .C(C),
        .fm(fm),
        .fM(fM),
        .fs(fs)
    );

    initial begin
        // Teste 1: A=0, B=0, C=0
        A = 0; B = 0; C = 0;
        #10; // Espera 10 unidades de tempo

        // Teste 2: A=0, B=0, C=1
        A = 0; B = 0; C = 1;
        #10;

        // Teste 3: A=0, B=1, C=0
        A = 0; B = 1; C = 0;
        #10;

        // Teste 4: A=0, B=1, C=1
        A = 0; B = 1; C = 1;
        #10;

        // Teste 5: A=1, B=0, C=0
        A = 1; B = 0; C = 0;
        #10;

        // Teste 6: A=1, B=0, C=1
        A = 1; B = 0; C = 1;
        #10;

        // Teste 7: A=1, B=1, C=0
        A = 1; B = 1; C = 0;
        #10;

        // Teste 8: A=1, B=1, C=1
        A = 1; B = 1; C = 1;
        #10;

        $finish; // Finaliza a simulação
    end     
endmodule

aula_05/sim/atividade1_tb.vcd
$date
	Fri Apr 24 09:19:43 2026
$end
$version
	Icarus Verilog
$end
$timescale
	1s
$end
$scope module atividade1_tb $end
$var wire 1 ! fs $end
$var wire 1 " fm $end
$var wire 1 # fM $end
$var reg 1 $ A $end
$var reg 1 % B $end
$var reg 1 & C $end
$scope module uut $end
$var wire 1 $ A $end
$var wire 1 % B $end
$var wire 1 & C $end
$var wire 1 # fM $end
$var wire 1 " fm $end
$var wire 1 ! fs $end
$upscope $end
$upscope $end
$enddefinitions $end
$comment Show the parameter values. $end
$dumpall
$end
#0
$dumpvars
0&
0%
0$
1#
1"
1!
$end
#10
0"
0#
0!
1&
#20
1"
1#
1!
0&
1%
#30
0"
0#
0!
1&
#40
1#
1"
1!
0&
0%
1$
#50
0"
0#
0!
1&
#60
1#
1"
1!
0&
1%
#70
0"
0#
0!
1&
