aula_05/src/atividade2.v
module atividade2 (
    input A,   //!Entrada A
    input B,   //!Entrada B
    input C,   //!Entrada C
    output fm, //!forma de soma de produtos, fm,
    output fM, //!forma de produtos de soma, fM e
    output fs  //!forma simplificada, fs 
);
    //fios internos
    wire not_A, not_B, not_C; //fios comuns
    wire Xm, Ym, Zm, Wm;  //fios para a forma fm
    wire XM, YM, ZM, WM;  //fios para a forma fM

    not not1(not_A, A);
    not not2(not_B, B);
    not not3(not_C, C);

    //Forma de soma de produtos, fm

    and and1(Xm, not_A, not_B, not_C);
    and and2(Ym, not_A, B, not_C);
    and and3(Zm, A, not_B, not_C);
    and and4(Wm, A, B, not_C);

    or or1(fm, Xm, Ym, Zm, Wm);

    //Forma de produtos de soma, fM

    or or2(XM, A, B, not_C);
    or or3(YM, A, not_B, not_C);
    or or4(ZM, not_A, B, not_C);
    or or5(WM, not_A, not_B, not_C);

    and and5(fM, XM, YM, ZM, WM);
    
    //Forma simplificada, fs

    not not4(fs, C);


endmodule

aula_05/src/atividade2_tb.v
module atividade2_tb;
    reg A, B, C; // Entradas
    wire fm, fM, fs; // Saídas

    //dumpfile
    initial begin
        $dumpfile("sim/atividade2_tb.vcd");
        $dumpvars(0, atividade2_tb);
    end
    
    // Instancia o módulo a ser testado
    atividade2 uut (
        .A(A),
        .B(B),
        .C(C),
        .fm(fm),
        .fM(fM),
        .fs(fs)
    );

    initial begin
        // Teste 1: A=0, B=0, C=0
        A = 0; B = 0; C = 0;
        #10; // Espera 10 unidades de tempo

        // Teste 2: A=0, B=0, C=1
        A = 0; B = 0; C = 1;
        #10;

        // Teste 3: A=0, B=1, C=0
        A = 0; B = 1; C = 0;
        #10;

        // Teste 4: A=0, B=1, C=1
        A = 0; B = 1; C = 1;
        #10;

        // Teste 5: A=1, B=0, C=0
        A = 1; B = 0; C = 0;
        #10;

        // Teste 6: A=1, B=0, C=1
        A = 1; B = 0; C = 1;
        #10;

        // Teste 7: A=1, B=1, C=0
        A = 1; B = 1; C = 0;
        #10;

        // Teste 8: A=1, B=1, C=1
        A = 1; B = 1; C = 1;
        #10;

        $finish; // Finaliza a simulação
    end     
endmodule

aula_05/sim/atividade2_tb.vcd
$date
	Fri Apr 24 09:20:44 2026
$end
$version
	Icarus Verilog
$end
$timescale
	1s
$end
$scope module atividade2_tb $end
$var wire 1 ! fs $end
$var wire 1 " fm $end
$var wire 1 # fM $end
$var reg 1 $ A $end
$var reg 1 % B $end
$var reg 1 & C $end
$scope module uut $end
$var wire 1 $ A $end
$var wire 1 % B $end
$var wire 1 & C $end
$var wire 1 ' WM $end
$var wire 1 ( Wm $end
$var wire 1 ) XM $end
$var wire 1 * Xm $end
$var wire 1 + YM $end
$var wire 1 , Ym $end
$var wire 1 - ZM $end
$var wire 1 . Zm $end
$var wire 1 # fM $end
$var wire 1 " fm $end
$var wire 1 ! fs $end
$var wire 1 / not_A $end
$var wire 1 0 not_B $end
$var wire 1 1 not_C $end
$upscope $end
$upscope $end
$enddefinitions $end
$comment Show the parameter values. $end
$dumpall
$end
#0
$dumpvars
11
10
1/
0.
1-
0,
1+
1*
1)
0(
1'
0&
0%
0$
1#
1"
1!
$end
#10
0"
0#
0*
0)
01
0!
1&
#20
1"
1,
1#
11
1!
00
1)
0&
1%
#30
0"
0#
0,
0+
01
0!
1&
#40
1#
1"
1.
11
1!
10
1-
0/
1+
0&
0%
1$
#50
0"
0#
0.
0-
01
0!
1&
#60
1"
1(
1#
11
1!
00
1-
0&
1%
#70
0"
0#
0(
0'
01
0!
1&
